{"title": "Anguriata", "link": "https://ricette.giallozafferano.it/Anguriata.html", "category": "Bevande", "ingredients": [{"name": "Cocomero (anguria)", "optional": false}, {"name": "Melone", "optional": false}, {"name": "Pesche", "optional": false}, {"name": "Ciliegie", "optional": false}, {"name": "Ananas", "optional": false}, {"name": "Limoni", "optional": false}, {"name": "Arance", "optional": false}, {"name": "Lamponi", "optional": false}, {"name": "Mirtilli", "optional": false}, {"name": "Fragole", "optional": false}, {"name": "Succo d'arancia", "optional": false}, {"name": "Succo di limone", "optional": false}, {"name": "Zucchero", "optional": false}, {"name": "Moscato", "optional": false}], "difficulty": "Molto facile", "rating": 4.6, "vegetarian": true, "lactoseFree": true}