{"title": "Bicchierini freddi di pesche al Dolcetto", "link": "https://ricette.giallozafferano.it/Bicchierini-freddi-di-pesche-al-Dolcetto.html", "category": "Dolci", "ingredients": [{"name": "Pesche gialle", "optional": false}, {"name": "Dolcetto", "optional": false}, {"name": "Zucchero", "optional": false}, {"name": "Limoni", "optional": false}, {"name": "Gelatina in fogli", "optional": false}, {"name": "Menta", "optional": false}], "difficulty": "Facile", "rating": 4.2, "vegetarian": false, "lactoseFree": false}