{"title": "Biscotti bicolore cacao e zucca", "link": "https://ricette.giallozafferano.it/Biscotti-bicolore-cacao-e-zucca.html", "category": "Dolci", "ingredients": [{"name": "Zucca", "optional": false}, {"name": "Farina 00", "optional": false}, {"name": "Fecola di patate", "optional": false}, {"name": "Burro", "optional": false}, {"name": "Tuorli", "optional": false}, {"name": "Zucchero", "optional": false}, {"name": "Cacao amaro in polvere", "optional": false}, {"name": "Confettura di fragole", "optional": false}], "difficulty": "Media", "rating": 5.0, "vegetarian": false, "lactoseFree": false}