{"title": "Ciaccia con l'uva", "link": "https://ricette.giallozafferano.it/Ciaccia-con-l-uva.html", "category": "Lievitati", "ingredients": [{"name": "Zucchero", "optional": false}, {"name": "Uva nera", "optional": false}, {"name": "Olio extravergine d'oliva", "optional": false}, {"name": "Lievito di birra fresco", "optional": false}, {"name": "Malto", "optional": true}, {"name": "Acqua", "optional": false}, {"name": "Farina 0", "optional": false}], "difficulty": "Facile", "rating": 4.6, "vegetarian": true, "lactoseFree": true}