{"title": "Colomba veloce ai frutti rossi", "link": "https://ricette.giallozafferano.it/Colomba-veloce-ai-frutti-rossi.html", "category": "Lievitati", "ingredients": [{"name": "Farina Manitoba", "optional": false}, {"name": "Acqua", "optional": false}, {"name": "Lievito di birra secco", "optional": false}, {"name": "Farina Manitoba", "optional": false}, {"name": "Zucchero", "optional": false}, {"name": "Burro", "optional": false}, {"name": "Latte intero", "optional": false}, {"name": "Latte condensato", "optional": false}, {"name": "Uova", "optional": false}, {"name": "Baccello di vaniglia", "optional": false}, {"name": "Scorza di limone", "optional": false}, {"name": "Scorza d'arancia", "optional": false}, {"name": "Olio extravergine d'oliva", "optional": true}, {"name": "Farina Manitoba", "optional": false}, {"name": "Burro", "optional": false}, {"name": "Uova", "optional": false}, {"name": "Frutti di bosco disidratati", "optional": false}, {"name": "Succo d'arancia", "optional": false}, {"name": "Mandorle in scaglie", "optional": true}, {"name": "Granella di zucchero", "optional": true}, {"name": "Mandorle pelate", "optional": false}, {"name": "Zucchero di canna", "optional": false}, {"name": "Latte condensato", "optional": false}, {"name": "Farina di mais fioretto", "optional": false}, {"name": "Amido di mais (maizena)", "optional": false}, {"name": "Albumi", "optional": false}], "difficulty": "Difficile", "rating": 4.3, "vegetarian": true, "lactoseFree": false}