{"title": "Conserva di melone al Porto", "link": "https://ricette.giallozafferano.it/Conserva-di-melone-al-Porto.html", "category": "Marmellate e Conserve", "ingredients": [{"name": "Melone", "optional": false}, {"name": "Vino porto", "optional": false}, {"name": "Acqua", "optional": false}, {"name": "Zucchero", "optional": false}, {"name": "Baccello di vaniglia", "optional": false}, {"name": "Cannella in stecche", "optional": false}, {"name": "Chiodi di garofano", "optional": false}], "difficulty": "Facile", "rating": 4.8, "vegetarian": true, "lactoseFree": true}