{"title": "Cotolette di zucca", "link": "https://ricette.giallozafferano.it/Cotolette-di-zucca.html", "category": "Secondi piatti", "ingredients": [{"name": "Zucca napoletana", "optional": false}, {"name": "Uova", "optional": false}, {"name": "Olio di semi di arachide", "optional": true}, {"name": "Pangrattato", "optional": false}, {"name": "Grana Padano DOP", "optional": false}, {"name": "Origano", "optional": true}, {"name": "Pepe nero", "optional": true}, {"name": "Sale fino", "optional": true}], "difficulty": "Facile", "rating": 4.3, "vegetarian": false, "lactoseFree": false}