{"title": "Cupcake rovesciati all'ananas", "link": "https://ricette.giallozafferano.it/Cupcake-rovesciati-all-ananas.html", "category": "Dolci", "ingredients": [{"name": "Ananas", "optional": false}, {"name": "Farina 00", "optional": false}, {"name": "Burro", "optional": false}, {"name": "Zucchero", "optional": false}, {"name": "Latte", "optional": false}, {"name": "Sale fino", "optional": true}, {"name": "Uova", "optional": false}, {"name": "Lievito in polvere per dolci", "optional": false}, {"name": "Zucchero di canna", "optional": false}, {"name": "Acqua", "optional": false}, {"name": "Burro", "optional": false}, {"name": "Ciliegie sciroppate", "optional": false}], "difficulty": "Facile", "rating": 5.0, "vegetarian": false, "lactoseFree": false}