{"title": "Daiquiri all’anguria con spiedini di melone", "link": "https://ricette.giallozafferano.it/Daiquiri-all-anguria-con-spiedini-di-melone.html", "category": "Bevande", "ingredients": [{"name": "Rum bianco", "optional": false}, {"name": "Cocomero (anguria)", "optional": false}, {"name": "Succo di lime", "optional": false}, {"name": "Sciroppo di zucchero", "optional": false}, {"name": "Menta", "optional": true}, {"name": "Melone cantalupo", "optional": false}, {"name": "Camembert", "optional": false}, {"name": "Olio al peperoncino", "optional": true}], "difficulty": "Molto facile", "rating": 3.0, "vegetarian": true, "lactoseFree": false}