{"title": "Fantasia di rustici", "link": "https://ricette.giallozafferano.it/Fantasia-di-rustici.html", "category": "Antipasti", "ingredients": [{"name": "Dischetti di pasta", "optional": false}, {"name": "Mozzarella", "optional": false}, {"name": "Prosciutto cotto", "optional": false}, {"name": "Dischetti di pasta", "optional": false}, {"name": "Spinaci", "optional": false}, {"name": "Feta", "optional": false}, {"name": "Olio extravergine d'oliva", "optional": false}, {"name": "Sale fino", "optional": true}, {"name": "Pepe nero", "optional": true}, {"name": "Dischetti di pasta", "optional": false}, {"name": "Wurstel", "optional": false}, {"name": "Semi di papavero", "optional": true}, {"name": "Uova", "optional": false}, {"name": "Dischetti di pasta", "optional": false}, {"name": "Passata di pomodoro", "optional": false}, {"name": "Scamorza (provola)", "optional": false}, {"name": "Acciughe sott'olio", "optional": false}], "difficulty": "Molto facile", "rating": 4.7, "vegetarian": false, "lactoseFree": false}