{"title": "Filetto di platessa al miele e erbe aromatiche", "link": "https://ricette.giallozafferano.it/Filetto-di-platessa-al-miele-e-erbe-aromatiche.html", "category": "Secondi piatti", "ingredients": [{"name": "Platessa", "optional": false}, {"name": "Aglio", "optional": false}, {"name": "Miele", "optional": false}, {"name": "Sale fino", "optional": true}, {"name": "Pepe nero", "optional": true}, {"name": "Rosmarino", "optional": true}, {"name": "Salvia", "optional": false}, {"name": "Mirto", "optional": false}, {"name": "Prezzemolo", "optional": false}, {"name": "Burro", "optional": false}, {"name": "Olio extravergine d'oliva", "optional": false}, {"name": "Brodo vegetale", "optional": true}], "difficulty": "Facile", "rating": 4.2, "vegetarian": false, "lactoseFree": false}