{"title": "Gyoza vegetariani", "link": "https://ricette.giallozafferano.it/Gyoza-vegetariani.html", "category": "Antipasti", "ingredients": [{"name": "Farina 00", "optional": false}, {"name": "Acqua", "optional": false}, {"name": "Sale fino", "optional": true}, {"name": "Tofu", "optional": false}, {"name": "Cavolo cappuccio", "optional": false}, {"name": "Funghi orecchioni o ostrica (Pleurotus)", "optional": false}, {"name": "Funghi shiitake", "optional": false}, {"name": "Carote", "optional": false}, {"name": "Cipollotto fresco", "optional": false}, {"name": "Aglio", "optional": false}, {"name": "Zenzero fresco", "optional": false}, {"name": "Salsa di soia", "optional": false}, {"name": "Olio di sesamo", "optional": false}, {"name": "Salsa sriracha", "optional": false}, {"name": "Olio di semi di girasole", "optional": true}, {"name": "Olio di semi di girasole", "optional": true}, {"name": "Acqua", "optional": false}, {"name": "Olio di sesamo", "optional": false}, {"name": "Salsa di soia", "optional": false}, {"name": "Aceto di riso", "optional": false}], "difficulty": "Difficile", "rating": 4.5, "vegetarian": true, "lactoseFree": false}