{"title": "Insalata di gamberi con salsa allo yogurt", "link": "https://ricette.giallozafferano.it/Insalata-di-gamberi-con-salsa-allo-yogurt.html", "category": "Piatti Unici", "ingredients": [{"name": "Cavolo cappuccio", "optional": false}, {"name": "Arance", "optional": false}, {"name": "Gamberi", "optional": false}, {"name": "Gherigli di noci", "optional": false}, {"name": "Olio di oliva", "optional": false}, {"name": "Scorza di limone", "optional": false}, {"name": "Spinacini", "optional": true}, {"name": "Olio extravergine d'oliva", "optional": false}, {"name": "Yogurt greco", "optional": false}, {"name": "Succo di lime", "optional": false}, {"name": "Menta", "optional": false}, {"name": "Timo", "optional": true}, {"name": "Sale fino", "optional": true}, {"name": "Pepe nero", "optional": true}], "difficulty": "Facile", "rating": 3.8, "vegetarian": false, "lactoseFree": false}