{"title": "Melone ripieno di frutta e gelato", "link": "https://ricette.giallozafferano.it/Melone-ripieno-di-frutta-e-gelato.html", "category": "Dolci", "ingredients": [{"name": "Melone", "optional": false}, {"name": "Mirtilli", "optional": false}, {"name": "Lamponi", "optional": false}, {"name": "Ribes rosso", "optional": false}, {"name": "Alchechengi", "optional": false}, {"name": "Gelato alla panna", "optional": false}, {"name": "Grand Marnier", "optional": false}, {"name": "Menta", "optional": false}], "difficulty": "Facile", "rating": 4.5, "vegetarian": false, "lactoseFree": false}