{"title": "Mousse allo zafferano con coulis di frutti rossi", "link": "https://ricette.giallozafferano.it/Mousse-allo-zafferano-con-coulis-di-frutti-rossi.html", "category": "Dolci", "ingredients": [{"name": "Panna fresca liquida", "optional": false}, {"name": "Latte intero", "optional": false}, {"name": "Zucchero", "optional": false}, {"name": "Gelatina in fogli", "optional": false}, {"name": "Zafferano", "optional": false}, {"name": "Lamponi", "optional": false}, {"name": "More", "optional": false}, {"name": "Ribes", "optional": false}, {"name": "Zucchero", "optional": false}, {"name": "Lamponi", "optional": false}, {"name": "Rosmarino", "optional": true}], "difficulty": "Facile", "rating": 5.0, "vegetarian": false, "lactoseFree": false}