{"title": "Nidi di tagliatelle al ragù di salsiccia", "link": "https://ricette.giallozafferano.it/Nidi-di-tagliatelle-al-ragu-di-salsiccia.html", "category": null, "ingredients": [{"name": "Passata di pomodoro", "optional": false}, {"name": "Salsiccia", "optional": false}, {"name": "Tagliatelle all'uovo", "optional": false}, {"name": "Grana Padano DOP", "optional": false}, {"name": "Carote", "optional": false}, {"name": "Cipolle dorate", "optional": false}, {"name": "Sedano", "optional": false}, {"name": "Olio extravergine d'oliva", "optional": false}, {"name": "Vino bianco", "optional": false}, {"name": "Sale fino", "optional": true}, {"name": "Pepe nero", "optional": true}], "difficulty": "Facile", "rating": 4.7, "vegetarian": false, "lactoseFree": false}