{"title": "Parigina", "link": "https://ricette.giallozafferano.it/Parigina.html", "category": "Lievitati", "ingredients": [{"name": "Farina 0", "optional": false}, {"name": "Acqua", "optional": false}, {"name": "Olio extravergine d'oliva", "optional": false}, {"name": "Sale fino", "optional": false}, {"name": "Lievito di birra fresco", "optional": false}, {"name": "Zucchero", "optional": false}, {"name": "Pomodori pelati", "optional": false}, {"name": "Caciocavallo", "optional": false}, {"name": "Prosciutto cotto", "optional": false}, {"name": "Pasta Sfoglia", "optional": false}, {"name": "Panna fresca liquida", "optional": false}, {"name": "Tuorli", "optional": false}, {"name": "Olio extravergine d'oliva", "optional": true}], "difficulty": "Media", "rating": 4.4, "vegetarian": false, "lactoseFree": false}