{"title": "Portobello burger", "link": "https://ricette.giallozafferano.it/Portobello-burger.html", "category": "Piatti Unici", "ingredients": [{"name": "Funghi portobello", "optional": false}, {"name": "Zucchine tonde", "optional": false}, {"name": "Melanzane tonde", "optional": false}, {"name": "Scamorza affumicata", "optional": false}, {"name": "Olio extravergine d'oliva", "optional": false}, {"name": "Maionese", "optional": false}, {"name": "Radicchio", "optional": false}, {"name": "Rosmarino", "optional": true}, {"name": "Sale fino", "optional": true}], "difficulty": "Media", "rating": 3.9, "vegetarian": true, "lactoseFree": false}