{"title": "Puccia salentina alle olive", "link": "https://ricette.giallozafferano.it/Puccia-salentina-alle-olive.html", "category": "Lievitati", "ingredients": [{"name": "Farina 00", "optional": false}, {"name": "Semola di grano duro rimacinata", "optional": false}, {"name": "Acqua", "optional": false}, {"name": "Lievito di birra secco", "optional": false}, {"name": "Malto", "optional": false}, {"name": "Patate", "optional": false}, {"name": "Farina 00", "optional": false}, {"name": "Semola di grano duro rimacinata", "optional": false}, {"name": "Olio extravergine d'oliva", "optional": false}, {"name": "Acqua", "optional": false}, {"name": "Sale fino", "optional": false}, {"name": "Olive nere", "optional": false}, {"name": "Semola di grano duro rimacinata", "optional": true}, {"name": "Mozzarella", "optional": false}, {"name": "Pomodori secchi sott'olio", "optional": false}], "difficulty": "Media", "rating": 4.6, "vegetarian": true, "lactoseFree": false}