{"title": "Riso tiepido con ceci, verdure arrosto e feta", "link": "https://ricette.giallozafferano.it/Riso-tiepido-con-ceci-verdure-arrosto-e-feta.html", "category": "Primi piatti", "ingredients": [{"name": "Riso integrale", "optional": false}, {"name": "Ceci precotti", "optional": false}, {"name": "Zucchine", "optional": false}, {"name": "Melanzane", "optional": false}, {"name": "Pomodorini datterini", "optional": false}, {"name": "Feta", "optional": false}, {"name": "Olio extravergine d'oliva", "optional": true}, {"name": "Origano", "optional": true}, {"name": "Olio extravergine d'oliva", "optional": false}, {"name": "Erbe aromatiche", "optional": true}], "difficulty": "Facile", "rating": 5.0, "vegetarian": true, "lactoseFree": false}