{"title": "Risotto cavolo nero e cozze", "link": "https://ricette.giallozafferano.it/Risotto-cavolo-nero-e-cozze.html", "category": "Primi piatti", "ingredients": [{"name": "Riso integrale", "optional": false}, {"name": "Cozze", "optional": false}, {"name": "Cavolo nero", "optional": false}, {"name": "Vino bianco", "optional": false}, {"name": "Prezzemolo", "optional": false}, {"name": "Aglio", "optional": false}, {"name": "Pepe rosa", "optional": true}, {"name": "Olio extravergine d'oliva", "optional": true}], "difficulty": "Facile", "rating": 5.0, "vegetarian": false, "lactoseFree": true}