{"title": "Risotto alla salsiccia e Nebbiolo", "link": "https://ricette.giallozafferano.it/Risotto-alla-salsiccia-e-Nebbiolo.html", "category": null, "ingredients": [{"name": "Riso Carnaroli", "optional": false}, {"name": "Olio extravergine d'oliva", "optional": false}, {"name": "Burro", "optional": false}, {"name": "Cipolle", "optional": false}, {"name": "Salsiccia di Bra", "optional": false}, {"name": "Brodo di carne", "optional": false}, {"name": "Vino bianco", "optional": false}, {"name": "Cipollotto fresco", "optional": false}, {"name": "Olio extravergine d'oliva", "optional": false}, {"name": "Burro", "optional": false}, {"name": "Nebbiolo", "optional": false}, {"name": "Rosmarino", "optional": true}, {"name": "Alloro", "optional": false}, {"name": "Burro", "optional": false}, {"name": "Parmigiano Reggiano DOP", "optional": false}], "difficulty": "Media", "rating": 4.6, "vegetarian": false, "lactoseFree": false}