{"title": "Risotto al cotechino, lenticchie e spumante", "link": "https://ricette.giallozafferano.it/Risotto-al-cotechino-lenticchie-e-spumante.html", "category": "Primi piatti", "ingredients": [{"name": "Riso Carnaroli", "optional": false}, {"name": "Cotechino Modena precotto", "optional": false}, {"name": "Spumante", "optional": false}, {"name": "Lenticchie", "optional": false}, {"name": "Brodo vegetale", "optional": false}, {"name": "Parmigiano Reggiano DOP", "optional": false}, {"name": "Scalogno", "optional": false}, {"name": "Burro", "optional": false}, {"name": "Olio extravergine d'oliva", "optional": true}], "difficulty": "Facile", "rating": 3.6, "vegetarian": false, "lactoseFree": false}