{"title": "Salame di cioccolato ai frutti esotici", "link": "https://ricette.giallozafferano.it/Salame-di-cioccolato-ai-frutti-esotici.html", "category": "Dolci", "ingredients": [{"name": "Cioccolato fondente", "optional": false}, {"name": "Burro", "optional": false}, {"name": "Biscotti Digestive", "optional": false}, {"name": "Mix di frutta secca/essiccata", "optional": false}, {"name": "Datteri", "optional": false}, {"name": "Zenzero", "optional": false}, {"name": "Cocco disidratato", "optional": false}, {"name": "Rum", "optional": false}, {"name": "Zucchero a velo", "optional": true}], "difficulty": "Facile", "rating": 4.1, "vegetarian": false, "lactoseFree": false}