{"title": "Salsiccia e patate alla birra", "link": "https://ricette.giallozafferano.it/Salsiccia-e-patate-alla-birra.html", "category": "Secondi piatti", "ingredients": [{"name": "Patate novelle", "optional": false}, {"name": "Salsiccia", "optional": false}, {"name": "Birra ambrata", "optional": false}, {"name": "Rosmarino", "optional": true}, {"name": "Olio extravergine d'oliva", "optional": false}, {"name": "Origano", "optional": true}, {"name": "Pepe nero", "optional": true}, {"name": "Sale fino", "optional": true}], "difficulty": "Facile", "rating": 4.9, "vegetarian": false, "lactoseFree": false}