{"title": "Salsa cocktail", "link": "https://ricette.giallozafferano.it/Salsa-cocktail.html", "category": "Antipasti", "ingredients": [{"name": "Worcestershire sauce", "optional": true}, {"name": "Salsa ketchup", "optional": false}, {"name": "Tabasco®", "optional": true}, {"name": "Brandy", "optional": true}, {"name": "Tuorli", "optional": false}, {"name": "Succo di limone", "optional": false}, {"name": "Olio di semi di girasole", "optional": false}, {"name": "Pepe nero", "optional": true}, {"name": "Sale fino", "optional": true}], "difficulty": "Facile", "rating": 4.4, "vegetarian": false, "lactoseFree": false}