{"title": "Schiacciate con pecorino sardo e miele", "link": "https://ricette.giallozafferano.it/Schiacciate-con-pecorino-sardo-e-miele.html", "category": "Antipasti", "ingredients": [{"name": "Schiacciate al forno", "optional": false}, {"name": "Pecorino sardo", "optional": false}, {"name": "Miele di corbezzolo", "optional": false}, {"name": "Mirto", "optional": true}, {"name": "Rosmarino", "optional": true}, {"name": "Brodo vegetale", "optional": true}], "difficulty": "Facile", "rating": 4.6, "vegetarian": false, "lactoseFree": false}