{"title": "Sgombro all'arancia", "link": "https://ricette.giallozafferano.it/Sgombro-all-arancia.html", "category": "Secondi piatti", "ingredients": [{"name": "Sgombro", "optional": false}, {"name": "Scorza d'arancia", "optional": false}, {"name": "Olio extravergine d'oliva", "optional": true}, {"name": "Succo d'arancia", "optional": false}, {"name": "Olio extravergine d'oliva", "optional": false}, {"name": "Aneto", "optional": true}, {"name": "Aglio", "optional": false}, {"name": "Pepe nero in grani", "optional": false}, {"name": "Sale fino", "optional": false}], "difficulty": "Facile", "rating": 4.2, "vegetarian": false, "lactoseFree": true}