{"title": "Sogliola alla mugnaia", "link": "https://ricette.giallozafferano.it/Sogliola-alla-mugnaia.html", "category": "Secondi piatti", "ingredients": [{"name": "Burro chiarificato", "optional": false}, {"name": "Farina 00", "optional": true}, {"name": "Succo di limone", "optional": false}, {"name": "Prezzemolo", "optional": false}, {"name": "Sale fino", "optional": true}, {"name": "Latte intero", "optional": true}, {"name": "Sogliola", "optional": false}], "difficulty": "Molto facile", "rating": 4.1, "vegetarian": false, "lactoseFree": false}