{"title": "Timballo di polenta e cotechino", "link": "https://ricette.giallozafferano.it/Timballo-di-polenta-e-cotechino.html", "category": "Piatti Unici", "ingredients": [{"name": "Farina istantanea per polenta", "optional": false}, {"name": "Cotechino precotto", "optional": false}, {"name": "Toma", "optional": false}, {"name": "Acqua", "optional": false}, {"name": "Olio extravergine d'oliva", "optional": false}, {"name": "Sale fino", "optional": false}, {"name": "Rosmarino", "optional": true}, {"name": "Senape", "optional": false}, {"name": "Pepe nero", "optional": true}, {"name": "Glassa di aceto balsamico", "optional": true}], "difficulty": "Media", "rating": 4.1, "vegetarian": false, "lactoseFree": false}