{"title": "Tortine pasquali con Nutella®", "link": "https://ricette.giallozafferano.it/Tortine-pasquali-con-Nutella.html", "category": "Dolci", "ingredients": [{"name": "Colomba", "optional": false}, {"name": "Ricotta vaccina", "optional": false}, {"name": "Panna fresca liquida", "optional": false}, {"name": "Zucchero a velo", "optional": false}, {"name": "Fragole", "optional": false}, {"name": "Scorza di limone", "optional": true}, {"name": "Burro", "optional": true}, {"name": "Nutella®", "optional": false}, {"name": "Fragole", "optional": false}], "difficulty": "Facile", "rating": 5.0, "vegetarian": false, "lactoseFree": false}