{"title": "Tronchetto salato con mousse di salmone, asparagi e mazzancolle", "link": "https://ricette.giallozafferano.it/Tronchetto-salato-con-mousse-di-salmone-asparagi-e-mazzancolle.html", "category": "Antipasti", "ingredients": [{"name": "Pancarrè", "optional": false}, {"name": "Asparagi", "optional": false}, {"name": "Mazzancolle", "optional": false}, {"name": "Salmone affumicato", "optional": false}, {"name": "Robiola", "optional": false}, {"name": "Panna fresca liquida", "optional": false}, {"name": "Erba cipollina", "optional": false}, {"name": "Sale fino", "optional": true}, {"name": "Pepe nero", "optional": true}, {"name": "Mazzancolle", "optional": false}, {"name": "Asparagi", "optional": false}, {"name": "Erba cipollina", "optional": true}], "difficulty": "Media", "rating": 4.3, "vegetarian": false, "lactoseFree": false}