{"title": "Trota al forno", "link": "https://ricette.giallozafferano.it/Trota-al-forno.html", "category": "Secondi piatti", "ingredients": [{"name": "Trota", "optional": false}, {"name": "Capperi sotto sale", "optional": false}, {"name": "Olive nere", "optional": false}, {"name": "Timo", "optional": true}, {"name": "Aglio", "optional": false}, {"name": "Pomodorini ciliegino", "optional": false}, {"name": "Acqua", "optional": false}, {"name": "Olio extravergine d'oliva", "optional": false}, {"name": "Sale fino", "optional": true}, {"name": "Olio extravergine d'oliva", "optional": false}], "difficulty": "Molto facile", "rating": 4.2, "vegetarian": false, "lactoseFree": true}