{"title": "Vin gelée", "link": "https://ricette.giallozafferano.it/Vin-gelee.html", "category": "Dolci", "ingredients": [{"name": "Vino rosso", "optional": false}, {"name": "Zucchero", "optional": false}, {"name": "Limoni", "optional": false}, {"name": "Arance", "optional": false}, {"name": "Noce moscata", "optional": false}, {"name": "Chiodi di garofano", "optional": false}, {"name": "Cannella in stecche", "optional": false}, {"name": "Anice stellato", "optional": false}, {"name": "Gelatina in fogli", "optional": false}], "difficulty": "Facile", "rating": 4.4, "vegetarian": false, "lactoseFree": true}